blgit/__init__.py
blgit/html.j2
blgit/index.css
blgit/index.j2
blgit/new_post.md
blgit/post.j2
blgit-0.0.42.dist-info/METADATA
blgit-0.0.42.dist-info/WHEEL
blgit-0.0.42.dist-info/entry_points.txt
blgit-0.0.42.dist-info/RECORD
