Metadata-Version: 2.1
Name: blgit
Version: 0.0.42
Summary: 
Author: Gilad Kutiel
Author-email: gilad.kutiel@gmail.com
Requires-Python: >=3.10,<4.0
Classifier: Programming Language :: Python :: 3
Classifier: Programming Language :: Python :: 3.10
Classifier: Programming Language :: Python :: 3.11
Classifier: Programming Language :: Python :: 3.12
Requires-Dist: cattrs (>=24.1.2,<25.0.0)
Requires-Dist: feedgen (>=1.0.0,<2.0.0)
Requires-Dist: frontmatter (>=3.0.8,<4.0.0)
Requires-Dist: jinja2 (>=3.1.4,<4.0.0)
Requires-Dist: markdown (>=3.7,<4.0)
Requires-Dist: typer (>=0.12.5,<0.13.0)
